netbox_prefix_map/__init__.py
netbox_prefix_map/urls.py
netbox_prefix_map/views.py
netbox_prefix_map/static/netbox_prefix_map/css/app.css
netbox_prefix_map/templates/netbox_prefix_map/prefix_map.html
netbox_prefix_map-0.1.2.dist-info/LICENSE
netbox_prefix_map-0.1.2.dist-info/METADATA
netbox_prefix_map-0.1.2.dist-info/WHEEL
netbox_prefix_map-0.1.2.dist-info/top_level.txt
netbox_prefix_map-0.1.2.dist-info/RECORD
