Metadata-Version: 2.1
Name: netbox-prefix-map
Version: 0.1.2
Summary: NetBox plugin to view usage of prefixes in an IP map
Home-page: https://github.com/Whaxion/netbox-prefix-map.git
License: Apache-2.0
License-File: LICENSE
